{
  "fluentMethods": true,
  "clientRootFolder": "SmartLernplatz",
  "relationships": [],
  "fields": [
    {
      "fieldName": "userId",
      "fieldType": "Long",
      "fieldValidateRules": ["required"]
    },
    {
      "fieldName": "pauseStartStamp",
      "fieldType": "ZonedDateTime"
    },
    {
      "fieldName": "pauseEndStamp",
      "fieldType": "ZonedDateTime"
    },
    {
      "fieldName": "bookingStartStamp",
      "fieldType": "ZonedDateTime"
    },
    {
      "fieldName": "bookingEndStamp",
      "fieldType": "ZonedDateTime"
    }
  ],
  "changelogDate": "20200825172800",
  "dto": "no",
  "searchEngine": false,
  "service": "serviceImpl",
  "entityTableName": "user_history",
  "databaseType": "sql",
  "readOnly": false,
  "jpaMetamodelFiltering": false,
  "pagination": "no",
  "microserviceName": "SmartLernplatz"
}
